employee_pkg/__init__.py
employee_pkg/best_employee.py
best_employee_finder_ashwinsabu20000-0.0.1.dist-info/LICENSE
best_employee_finder_ashwinsabu20000-0.0.1.dist-info/METADATA
best_employee_finder_ashwinsabu20000-0.0.1.dist-info/WHEEL
best_employee_finder_ashwinsabu20000-0.0.1.dist-info/top_level.txt
best_employee_finder_ashwinsabu20000-0.0.1.dist-info/RECORD
