Metadata-Version: 2.1
Name: best-employee-finder-ashwinsabu20000
Version: 0.0.1
Summary: A package used to find the best employee in an organization
Home-page: https://github.com/pypa/sampleproject
Author: Ashwin Sabu
Author-email: ashiwnsabu2000@gmail.com
Classifier: Programming Language :: Python :: 3
Classifier: License :: OSI Approved :: MIT License
Classifier: Operating System :: OS Independent
Requires-Python: >=3.6
License-File: LICENSE
